{"version":1,"resource":"file:///home/holelulu/projects/ai-trader/server-side/test.py","entries":[{"id":"u8aN.py","timestamp":1737746957064},{"id":"opjH.py","timestamp":1737746971331},{"id":"cMc4.py","timestamp":1737746986298},{"id":"T5wg.py","timestamp":1737747032186},{"id":"g25G.py","timestamp":1737747043886},{"id":"ipPx.py","timestamp":1737747062080},{"id":"vL42.py","timestamp":1737747100324},{"id":"mkP6.py","timestamp":1737747578843},{"id":"7wpE.py","timestamp":1737747605181},{"id":"Dmf7.py","timestamp":1737747655065}]}