{"version":1,"resource":"file:///home/holelulu/projects/c%2B%2B/include/snake.h","entries":[{"id":"d2ym.h","timestamp":1737581526817},{"id":"ojgc.h","timestamp":1737581547204},{"id":"ANAH.h","timestamp":1737581563088},{"id":"A0zK.h","timestamp":1737581578622},{"id":"hQHP.h","timestamp":1737581602269},{"id":"NRSS.h","timestamp":1737581622263},{"id":"MU6C.h","timestamp":1737634780516},{"id":"5UiD.h","timestamp":1737634962247},{"id":"aRHh.h","timestamp":1737637274003},{"id":"LdO9.h","timestamp":1737637566478},{"id":"4rB7.h","timestamp":1737641133028},{"id":"Wi6g.h","timestamp":1737642520019},{"id":"SLrd.h","timestamp":1737643251270},{"id":"YJTi.h","timestamp":1737643336811},{"id":"Gu12.h","timestamp":1737643775922}]}